ollama_fastapi/__init__.py
ollama_fastapi/cli.py
ollama_fastapi/client.py
ollama_fastapi/main.py
ollama_fastapi-0.1.1.dist-info/licenses/LICENSE
ollama_fastapi-0.1.1.dist-info/METADATA
ollama_fastapi-0.1.1.dist-info/WHEEL
ollama_fastapi-0.1.1.dist-info/entry_points.txt
ollama_fastapi-0.1.1.dist-info/top_level.txt
ollama_fastapi-0.1.1.dist-info/RECORD
