Metadata-Version: 2.4
Name: ollama-fastapi
Version: 0.1.1
Summary: FastAPI wrapper for running Ollama locally
Author-email: Amal Alexander <amalalex95@gmail.com>
License: MIT
Requires-Python: >=3.8
License-File: LICENSE
Requires-Dist: fastapi
Requires-Dist: uvicorn
Dynamic: license-file
